rhea/__init__.py
rhea/config.py
rhea/constants.py
rhea/exceptions.py
rhea/manager.py
rhea/parser.py
rhea/reader.py
rhea/specs.py
rhea/types.py
rhea/utils.py
tests/__init__.py
tests/test_manager.py
tests/test_parser.py
tests/test_reader.py
rhea-0.5.5.dist-info/LICENSE
rhea-0.5.5.dist-info/METADATA
rhea-0.5.5.dist-info/WHEEL
rhea-0.5.5.dist-info/top_level.txt
rhea-0.5.5.dist-info/RECORD
