Metadata-Version: 2.1
Name: rhea
Version: 0.5.5
Summary: Efficient environment variables management and typing for python.
Home-page: https://github.com/polyaxon/rhea
Author: Mourad Mourafiq
Author-email: mourad.mourafiq@gmail.com
Maintainer: Mourad Mourafiq
Maintainer-email: mourad.mourafiq@gmail.com
License: MIT
Keywords: polyaxon,dotenv,environ,environment,env-vars,.env,django
Platform: any
Classifier: Programming Language :: Python
Classifier: Operating System :: OS Independent
Classifier: Intended Audience :: Developers
Classifier: Intended Audience :: Science/Research
Classifier: Topic :: Scientific/Engineering :: Artificial Intelligence
Classifier: Development Status :: 5 - Production/Stable
Classifier: Environment :: Web Environment
Classifier: Programming Language :: Python :: 2
Classifier: Programming Language :: Python :: 3
Classifier: Topic :: Internet :: WWW/HTTP
Requires-Dist: PyYAML (>=5.1)
Requires-Dist: six (>=1.12.0)
